{"timestamp": "2026-06-19T23:00:00Z", "equipment_id": "EXC-001", "metadata": {"firmware": "v2.1.4", "protocol": "OPC-UA"}, "metrics": {"engine_temp_c": 81.71, "hydraulic_psi": 3046.53, "rpm": 1810.75}}
{"timestamp": "2026-06-19T23:01:00Z", "equipment_id": "EXC-001", "metadata": {"firmware": "v2.1.4", "protocol": "OPC-UA"}, "metrics": {"engine_temp_c": 84.09, "hydraulic_psi": 3097.65, "rpm": 1753.94}}
{"timestamp": "2026-06-19T23:02:00Z", "equipment_id": "EXC-001", "metadata": {"firmware": "v2.1.4", "protocol": "OPC-UA"}, "metrics": {"engine_temp_c": 85.24, "hydraulic_psi": 2967.92, "rpm": 1750.44}}
{"timestamp": "2026-06-19T23:03:00Z", "equipment_id": "EXC-001", "metadata": {"firmware": "v2.1.4", "protocol": "OPC-UA"}, "metrics": {"engine_temp_c": 82.37, "hydraulic_psi": 3148.21, "rpm": 1822.77}}
{"timestamp": "2026-06-19T23:04:00Z", "equipment_id": "EXC-001", "metadata": {"firmware": "v2.1.4", "protocol": "OPC-UA"}, "metrics": {"engine_temp_c": 85.19, "hydraulic_psi": 2892.98, "rpm": 1796.13}}
{"timestamp": "2026-06-19T23:05:00Z", "equipment_id": "EXC-001", "metadata": {"firmware": "v2.1.4", "protocol": "OPC-UA"}, "metrics": {"engine_temp_c": 83.93, "hydraulic_psi": 3072.92, "rpm": 1833.98}}
{"timestamp": "2026-06-19T23:06:00Z", "equipment_id": "EXC-001", "metadata": {"firmware": "v2.1.4", "protocol": "OPC-UA"}, "metrics": {"engine_temp_c": 88.61, "hydraulic_psi": 2824.47, "rpm": 1846.22}}
{"timestamp": "2026-06-19T23:07:00Z", "equipment_id": "EXC-001", "metadata": {"firmware": "v2.1.4", "protocol": "OPC-UA"}, "metrics": {"engine_temp_c": 83.81, "hydraulic_psi": 11834.84, "rpm": 1849.93}}
{"timestamp": "2026-06-19T23:08:00Z", "equipment_id": "EXC-001", "metadata": {"firmware": "v2.1.4", "protocol": "OPC-UA"}, "metrics": {"engine_temp_c": 81.71, "hydraulic_psi": 2835.87, "rpm": 1777.56}}
{"timestamp": "2026-06-19T23:09:00Z", "equipment_id": "EXC-001", "metadata": {"firmware": "v2.1.4", "protocol": "OPC-UA"}, "metrics": {"engine_temp_c": 86.33, "hydraulic_psi": 2858.32, "rpm": 1845.47}}
{"timestamp": "2026-06-19T23:10:00Z", "equipment_id": "EXC-001", "metadata": {"firmware": "v2.1.4", "protocol": "OPC-UA"}, "metrics": {"engine_temp_c": 80.47, "hydraulic_psi": 2862.33, "rpm": 1839.89}}
{"timestamp": "2026-06-19T23:11:00Z", "equipment_id": "EXC-001", "metadata": {"firmware": "v2.1.4", "protocol": "OPC-UA"}, "metrics": {"engine_temp_c": 82.31, "hydraulic_psi": 2904.99, "rpm": 7179.74}}
{"timestamp": "2026-06-19T23:12:00Z", "equipment_id": "EXC-001", "metadata": {"firmware": "v2.1.4", "protocol": "OPC-UA"}, "metrics": {"engine_temp_c": 88.55, "hydraulic_psi": 3185.19, "rpm": 1839.03}}
{"timestamp": "2026-06-19T23:13:00Z", "equipment_id": "EXC-001", "metadata": {"firmware": "v2.1.4", "protocol": "OPC-UA"}, "metrics": {"engine_temp_c": 80.09, "hydraulic_psi": 3074.43, "rpm": 1791.82}}
{"timestamp": "2026-06-19T23:14:00Z", "equipment_id": "EXC-001", "metadata": {"firmware": "v2.1.4", "protocol": "OPC-UA"}, "metrics": {"engine_temp_c": 84.44, "hydraulic_psi": 3183.65, "rpm": 1842.59}}
{"timestamp": "2026-06-19T23:15:00Z", "equipment_id": "EXC-001", "metadata": {"firmware": "v2.1.4", "protocol": "OPC-UA"}, "metrics": {"engine_temp_c": 80.76, "hydraulic_psi": 3134.29, "rpm": 1781.75}}
{"timestamp": "2026-06-19T23:16:00Z", "equipment_id": "EXC-001", "metadata": {"firmware": "v2.1.4", "protocol": "OPC-UA"}, "metrics": {"engine_temp_c": 89.35, "hydraulic_psi": 3164.49, "rpm": 1830.07}}
{"timestamp": "2026-06-19T23:17:00Z", "equipment_id": "EXC-001", "metadata": {"firmware": "v2.1.4", "protocol": "OPC-UA"}, "metrics": {"engine_temp_c": 81.77, "hydraulic_psi": 2805.19, "rpm": 1817.98}}
{"timestamp": "2026-06-19T23:18:00Z", "equipment_id": "EXC-001", "metadata": {"firmware": "v2.1.4", "protocol": "OPC-UA"}, "metrics": {"engine_temp_c": 84.51, "hydraulic_psi": 2871.17, "rpm": 4798.45}}
{"timestamp": "2026-06-19T23:19:00Z", "equipment_id": "EXC-001", "metadata": {"firmware": "v2.1.4", "protocol": "OPC-UA"}, "metrics": {"engine_temp_c": 84.55, "hydraulic_psi": null, "rpm": 1791.73}}
{"timestamp": "2026-06-19T23:20:00Z", "equipment_id": "EXC-001", "metadata": {"firmware": "v2.1.4", "protocol": "OPC-UA"}, "metrics": {"engine_temp_c": 86.9, "hydraulic_psi": 3089.84, "rpm": 1789.69}}
{"timestamp": "2026-06-19T23:21:00Z", "equipment_id": "EXC-001", "metadata": {"firmware": "v2.1.4", "protocol": "OPC-UA"}, "metrics": {"engine_temp_c": 87.81, "hydraulic_psi": 2803.31, "rpm": 1788.58}}
{"timestamp": "2026-06-19T23:22:00Z", "equipment_id": "EXC-001", "metadata": {"firmware": "v2.1.4", "protocol": "OPC-UA"}, "metrics": {"engine_temp_c": 82.33, "hydraulic_psi": 2926.42, "rpm": 1829.57}}
{"timestamp": "2026-06-19T23:23:00Z", "equipment_id": "EXC-001", "metadata": {"firmware": "v2.1.4", "protocol": "OPC-UA"}, "metrics": {"engine_temp_c": 81.41, "hydraulic_psi": 3173.86, "rpm": null}}
{"timestamp": "2026-06-19T23:24:00Z", "equipment_id": "EXC-001", "metadata": {"firmware": "v2.1.4", "protocol": "OPC-UA"}, "metrics": {"engine_temp_c": 84.17, "hydraulic_psi": 2861.92, "rpm": 1775.64}}
{"timestamp": "2026-06-19T23:25:00Z", "equipment_id": "EXC-001", "metadata": {"firmware": "v2.1.4", "protocol": "OPC-UA"}, "metrics": {"engine_temp_c": 89.83, "hydraulic_psi": 3061.3, "rpm": 1773.38}}
{"timestamp": "2026-06-19T23:26:00Z", "equipment_id": "EXC-001", "metadata": {"firmware": "v2.1.4", "protocol": "OPC-UA"}, "metrics": {"engine_temp_c": 87.17, "hydraulic_psi": 2814.18, "rpm": 1768.19}}
{"timestamp": "2026-06-19T23:27:00Z", "equipment_id": "EXC-001", "metadata": {"firmware": "v2.1.4", "protocol": "OPC-UA"}, "metrics": {"engine_temp_c": 88.19, "hydraulic_psi": 2839.2, "rpm": 1776.09}}
{"timestamp": "2026-06-19T23:28:00Z", "equipment_id": "EXC-001", "metadata": {"firmware": "v2.1.4", "protocol": "OPC-UA"}, "metrics": {"engine_temp_c": 89.49, "hydraulic_psi": 7510.3, "rpm": 1751.2}}
{"timestamp": "2026-06-19T23:29:00Z", "equipment_id": "EXC-001", "metadata": {"firmware": "v2.1.4", "protocol": "OPC-UA"}, "metrics": {"engine_temp_c": 83.19, "hydraulic_psi": 3004.56, "rpm": 1821.53}}
{"timestamp": "2026-06-19T23:30:00Z", "equipment_id": "EXC-001", "metadata": {"firmware": "v2.1.4", "protocol": "OPC-UA"}, "metrics": {"engine_temp_c": 81.93, "hydraulic_psi": 3010.56, "rpm": 1812.85}}
{"timestamp": "2026-06-19T23:31:00Z", "equipment_id": "EXC-001", "metadata": {"firmware": "v2.1.4", "protocol": "OPC-UA"}, "metrics": {"engine_temp_c": 88.27, "hydraulic_psi": 2948.16, "rpm": 1843.76}}
{"timestamp": "2026-06-19T23:32:00Z", "equipment_id": "EXC-001", "metadata": {"firmware": "v2.1.4", "protocol": "OPC-UA"}, "metrics": {"engine_temp_c": 88.93, "hydraulic_psi": 3159.4, "rpm": 1821.01}}
{"timestamp": "2026-06-19T23:33:00Z", "equipment_id": "EXC-001", "metadata": {"firmware": "v2.1.4", "protocol": "OPC-UA"}, "metrics": {"engine_temp_c": 89.93, "hydraulic_psi": 3129.34, "rpm": 1832.07}}
{"timestamp": "2026-06-19T23:34:00Z", "equipment_id": "EXC-001", "metadata": {"firmware": "v2.1.4", "protocol": "OPC-UA"}, "metrics": {"engine_temp_c": 89.86, "hydraulic_psi": 2869.97, "rpm": 1760.34}}
{"timestamp": "2026-06-19T23:35:00Z", "equipment_id": "EXC-001", "metadata": {"firmware": "v2.1.4", "protocol": "OPC-UA"}, "metrics": {"engine_temp_c": 81.44, "hydraulic_psi": 2945.73, "rpm": 1831.14}}
{"timestamp": "2026-06-19T23:36:00Z", "equipment_id": "EXC-001", "metadata": {"firmware": "v2.1.4", "protocol": "OPC-UA"}, "metrics": {"engine_temp_c": 86.28, "hydraulic_psi": 3174.5, "rpm": 1841.25}}
{"timestamp": "2026-06-19T23:37:00Z", "equipment_id": "EXC-001", "metadata": {"firmware": "v2.1.4", "protocol": "OPC-UA"}, "metrics": {"engine_temp_c": 83.25, "hydraulic_psi": 3046.72, "rpm": 1836.6}}
{"timestamp": "2026-06-19T23:38:00Z", "equipment_id": "EXC-001", "metadata": {"firmware": "v2.1.4", "protocol": "OPC-UA"}, "metrics": {"engine_temp_c": 84.83, "hydraulic_psi": 2932.15, "rpm": 1819.92}}
{"timestamp": "2026-06-19T23:39:00Z", "equipment_id": "EXC-001", "metadata": {"firmware": "v2.1.4", "protocol": "OPC-UA"}, "metrics": {"engine_temp_c": 81.89, "hydraulic_psi": 2803.13, "rpm": 1837.22}}
{"timestamp": "2026-06-19T23:40:00Z", "equipment_id": "EXC-001", "metadata": {"firmware": "v2.1.4", "protocol": "OPC-UA"}, "metrics": {"engine_temp_c": 84.49, "hydraulic_psi": 3148.4, "rpm": 1802.1}}
{"timestamp": "2026-06-19T23:41:00Z", "equipment_id": "EXC-001", "metadata": {"firmware": "v2.1.4", "protocol": "OPC-UA"}, "metrics": {"engine_temp_c": 86.07, "hydraulic_psi": 2826.98, "rpm": 1841.23}}
{"timestamp": "2026-06-19T23:42:00Z", "equipment_id": "EXC-001", "metadata": {"firmware": "v2.1.4", "protocol": "OPC-UA"}, "metrics": {"engine_temp_c": 85.11, "hydraulic_psi": 3195.37, "rpm": 1778.37}}
{"timestamp": "2026-06-19T23:43:00Z", "equipment_id": "EXC-001", "metadata": {"firmware": "v2.1.4", "protocol": "OPC-UA"}, "metrics": {"engine_temp_c": 86.47, "hydraulic_psi": 2866.52, "rpm": 1778.66}}
{"timestamp": "2026-06-19T23:44:00Z", "equipment_id": "EXC-001", "metadata": {"firmware": "v2.1.4", "protocol": "OPC-UA"}, "metrics": {"engine_temp_c": 85.9, "hydraulic_psi": 11323.53, "rpm": 1840.37}}
{"timestamp": "2026-06-19T23:45:00Z", "equipment_id": "EXC-001", "metadata": {"firmware": "v2.1.4", "protocol": "OPC-UA"}, "metrics": {"engine_temp_c": 88.04, "hydraulic_psi": 3088.02, "rpm": 1843.35}}
{"timestamp": "2026-06-19T23:46:00Z", "equipment_id": "EXC-001", "metadata": {"firmware": "v2.1.4", "protocol": "OPC-UA"}, "metrics": {"engine_temp_c": 85.95, "hydraulic_psi": 10358.13, "rpm": 1844.26}}
{"timestamp": "2026-06-19T23:47:00Z", "equipment_id": "EXC-001", "metadata": {"firmware": "v2.1.4", "protocol": "OPC-UA"}, "metrics": {"engine_temp_c": 82.6, "hydraulic_psi": 3117.79, "rpm": 1795.58}}
{"timestamp": "2026-06-19T23:48:00Z", "equipment_id": "EXC-001", "metadata": {"firmware": "v2.1.4", "protocol": "OPC-UA"}, "metrics": {"engine_temp_c": 82.07, "hydraulic_psi": 2828.55, "rpm": 1824.66}}
{"timestamp": "2026-06-19T23:49:00Z", "equipment_id": "EXC-001", "metadata": {"firmware": "v2.1.4", "protocol": "OPC-UA"}, "metrics": {"engine_temp_c": 81.07, "hydraulic_psi": 2857.25, "rpm": 1763.35}}
{"timestamp": "2026-06-19T23:50:00Z", "equipment_id": "EXC-001", "metadata": {"firmware": "v2.1.4", "protocol": "OPC-UA"}, "metrics": {"engine_temp_c": 85.94, "hydraulic_psi": 2887.24, "rpm": 1814.06}}
{"timestamp": "2026-06-19T23:51:00Z", "equipment_id": "EXC-001", "metadata": {"firmware": "v2.1.4", "protocol": "OPC-UA"}, "metrics": {"engine_temp_c": 86.6, "hydraulic_psi": 2834.4, "rpm": null}}
{"timestamp": "2026-06-19T23:52:00Z", "equipment_id": "EXC-001", "metadata": {"firmware": "v2.1.4", "protocol": "OPC-UA"}, "metrics": {"engine_temp_c": 85.49, "hydraulic_psi": 2900.94, "rpm": 1757.02}}
{"timestamp": "2026-06-19T23:53:00Z", "equipment_id": "EXC-001", "metadata": {"firmware": "v2.1.4", "protocol": "OPC-UA"}, "metrics": {"engine_temp_c": 80.28, "hydraulic_psi": 3080.6, "rpm": 1810.96}}
{"timestamp": "2026-06-19T23:54:00Z", "equipment_id": "EXC-001", "metadata": {"firmware": "v2.1.4", "protocol": "OPC-UA"}, "metrics": {"engine_temp_c": 85.45, "hydraulic_psi": 2912.14, "rpm": 1821.07}}
{"timestamp": "2026-06-19T23:55:00Z", "equipment_id": "EXC-001", "metadata": {"firmware": "v2.1.4", "protocol": "OPC-UA"}, "metrics": {"engine_temp_c": 89.93, "hydraulic_psi": 3010.3, "rpm": 1849.28}}
{"timestamp": "2026-06-19T23:56:00Z", "equipment_id": "EXC-001", "metadata": {"firmware": "v2.1.4", "protocol": "OPC-UA"}, "metrics": {"engine_temp_c": 84.76, "hydraulic_psi": 2923.78, "rpm": 1825.9}}
{"timestamp": "2026-06-19T23:57:00Z", "equipment_id": "EXC-001", "metadata": {"firmware": "v2.1.4", "protocol": "OPC-UA"}, "metrics": {"engine_temp_c": 89.01, "hydraulic_psi": 3099.81, "rpm": 1842.62}}
{"timestamp": "2026-06-19T23:58:00Z", "equipment_id": "EXC-001", "metadata": {"firmware": "v2.1.4", "protocol": "OPC-UA"}, "metrics": {"engine_temp_c": 88.34, "hydraulic_psi": 3008.3, "rpm": 1833.57}}
{"timestamp": "2026-06-19T23:59:00Z", "equipment_id": "EXC-001", "metadata": {"firmware": "v2.1.4", "protocol": "OPC-UA"}, "metrics": {"engine_temp_c": 85.04, "hydraulic_psi": 3069.32, "rpm": 1764.71}}
