{"timestamp": "2026-06-20T18:00:00Z", "equipment_id": "EXC-001", "metadata": {"firmware": "v2.1.4", "protocol": "OPC-UA"}, "metrics": {"engine_temp_c": 83.22, "hydraulic_psi": 3142.19, "rpm": 1818.9}}
{"timestamp": "2026-06-20T18:01:00Z", "equipment_id": "EXC-001", "metadata": {"firmware": "v2.1.4", "protocol": "OPC-UA"}, "metrics": {"engine_temp_c": 86.5, "hydraulic_psi": 3196.79, "rpm": 1793.62}}
{"timestamp": "2026-06-20T18:02:00Z", "equipment_id": "EXC-001", "metadata": {"firmware": "v2.1.4", "protocol": "OPC-UA"}, "metrics": {"engine_temp_c": 88.54, "hydraulic_psi": 3185.97, "rpm": 1765.35}}
{"timestamp": "2026-06-20T18:03:00Z", "equipment_id": "EXC-001", "metadata": {"firmware": "v2.1.4", "protocol": "OPC-UA"}, "metrics": {"engine_temp_c": 80.82, "hydraulic_psi": 2999.17, "rpm": 1846.0}}
{"timestamp": "2026-06-20T18:04:00Z", "equipment_id": "EXC-001", "metadata": {"firmware": "v2.1.4", "protocol": "OPC-UA"}, "metrics": {"engine_temp_c": 85.84, "hydraulic_psi": 2908.38, "rpm": 1779.47}}
{"timestamp": "2026-06-20T18:05:00Z", "equipment_id": "EXC-001", "metadata": {"firmware": "v2.1.4", "protocol": "OPC-UA"}, "metrics": {"engine_temp_c": 84.15, "hydraulic_psi": 3009.14, "rpm": 1790.01}}
{"timestamp": "2026-06-20T18:06:00Z", "equipment_id": "EXC-001", "metadata": {"firmware": "v2.1.4", "protocol": "OPC-UA"}, "metrics": {"engine_temp_c": 86.51, "hydraulic_psi": 3077.77, "rpm": 1841.82}}
{"timestamp": "2026-06-20T18:07:00Z", "equipment_id": "EXC-001", "metadata": {"firmware": "v2.1.4", "protocol": "OPC-UA"}, "metrics": {"engine_temp_c": 85.78, "hydraulic_psi": 2960.39, "rpm": 1805.58}}
{"timestamp": "2026-06-20T18:08:00Z", "equipment_id": "EXC-001", "metadata": {"firmware": "v2.1.4", "protocol": "OPC-UA"}, "metrics": {"engine_temp_c": 235.45, "hydraulic_psi": 2864.08, "rpm": 1837.46}}
{"timestamp": "2026-06-20T18:09:00Z", "equipment_id": "EXC-001", "metadata": {"firmware": "v2.1.4", "protocol": "OPC-UA"}, "metrics": {"engine_temp_c": 84.57, "hydraulic_psi": 2970.39, "rpm": 1849.64}}
{"timestamp": "2026-06-20T18:10:00Z", "equipment_id": "EXC-001", "metadata": {"firmware": "v2.1.4", "protocol": "OPC-UA"}, "metrics": {"engine_temp_c": 89.61, "hydraulic_psi": null, "rpm": 1794.73}}
{"timestamp": "2026-06-20T18:11:00Z", "equipment_id": "EXC-001", "metadata": {"firmware": "v2.1.4", "protocol": "OPC-UA"}, "metrics": {"engine_temp_c": 89.35, "hydraulic_psi": 3081.29, "rpm": 1823.38}}
{"timestamp": "2026-06-20T18:12:00Z", "equipment_id": "EXC-001", "metadata": {"firmware": "v2.1.4", "protocol": "OPC-UA"}, "metrics": {"engine_temp_c": 88.71, "hydraulic_psi": 3192.27, "rpm": 1833.36}}
{"timestamp": "2026-06-20T18:13:00Z", "equipment_id": "EXC-001", "metadata": {"firmware": "v2.1.4", "protocol": "OPC-UA"}, "metrics": {"engine_temp_c": 84.06, "hydraulic_psi": 2957.91, "rpm": 1844.3}}
{"timestamp": "2026-06-20T18:14:00Z", "equipment_id": "EXC-001", "metadata": {"firmware": "v2.1.4", "protocol": "OPC-UA"}, "metrics": {"engine_temp_c": 88.63, "hydraulic_psi": 2874.78, "rpm": 1750.51}}
{"timestamp": "2026-06-20T18:15:00Z", "equipment_id": "EXC-001", "metadata": {"firmware": "v2.1.4", "protocol": "OPC-UA"}, "metrics": {"engine_temp_c": 89.35, "hydraulic_psi": 2970.2, "rpm": 1773.28}}
{"timestamp": "2026-06-20T18:16:00Z", "equipment_id": "EXC-001", "metadata": {"firmware": "v2.1.4", "protocol": "OPC-UA"}, "metrics": {"engine_temp_c": 88.89, "hydraulic_psi": 2899.43, "rpm": 1779.54}}
{"timestamp": "2026-06-20T18:17:00Z", "equipment_id": "EXC-001", "metadata": {"firmware": "v2.1.4", "protocol": "OPC-UA"}, "metrics": {"engine_temp_c": 84.53, "hydraulic_psi": 2979.32, "rpm": 1780.23}}
{"timestamp": "2026-06-20T18:18:00Z", "equipment_id": "EXC-001", "metadata": {"firmware": "v2.1.4", "protocol": "OPC-UA"}, "metrics": {"engine_temp_c": 82.18, "hydraulic_psi": 3135.06, "rpm": 1807.72}}
{"timestamp": "2026-06-20T18:19:00Z", "equipment_id": "EXC-001", "metadata": {"firmware": "v2.1.4", "protocol": "OPC-UA"}, "metrics": {"engine_temp_c": 87.24, "hydraulic_psi": 3131.1, "rpm": 1755.04}}
{"timestamp": "2026-06-20T18:20:00Z", "equipment_id": "EXC-001", "metadata": {"firmware": "v2.1.4", "protocol": "OPC-UA"}, "metrics": {"engine_temp_c": 85.1, "hydraulic_psi": 2911.25, "rpm": 1779.35}}
{"timestamp": "2026-06-20T18:21:00Z", "equipment_id": "EXC-001", "metadata": {"firmware": "v2.1.4", "protocol": "OPC-UA"}, "metrics": {"engine_temp_c": 81.93, "hydraulic_psi": 3124.87, "rpm": 1758.04}}
{"timestamp": "2026-06-20T18:22:00Z", "equipment_id": "EXC-001", "metadata": {"firmware": "v2.1.4", "protocol": "OPC-UA"}, "metrics": {"engine_temp_c": 88.9, "hydraulic_psi": 3046.33, "rpm": 1826.15}}
{"timestamp": "2026-06-20T18:23:00Z", "equipment_id": "EXC-001", "metadata": {"firmware": "v2.1.4", "protocol": "OPC-UA"}, "metrics": {"engine_temp_c": 83.69, "hydraulic_psi": 2851.5, "rpm": 1751.75}}
{"timestamp": "2026-06-20T18:24:00Z", "equipment_id": "EXC-001", "metadata": {"firmware": "v2.1.4", "protocol": "OPC-UA"}, "metrics": {"engine_temp_c": 86.44, "hydraulic_psi": 3108.22, "rpm": 1795.6}}
{"timestamp": "2026-06-20T18:25:00Z", "equipment_id": "EXC-001", "metadata": {"firmware": "v2.1.4", "protocol": "OPC-UA"}, "metrics": {"engine_temp_c": 81.54, "hydraulic_psi": 2953.27, "rpm": 1797.13}}
{"timestamp": "2026-06-20T18:26:00Z", "equipment_id": "EXC-001", "metadata": {"firmware": "v2.1.4", "protocol": "OPC-UA"}, "metrics": {"engine_temp_c": 85.05, "hydraulic_psi": 3053.84, "rpm": 1766.37}}
{"timestamp": "2026-06-20T18:27:00Z", "equipment_id": "EXC-001", "metadata": {"firmware": "v2.1.4", "protocol": "OPC-UA"}, "metrics": {"engine_temp_c": 87.97, "hydraulic_psi": 2987.59, "rpm": 1759.35}}
{"timestamp": "2026-06-20T18:28:00Z", "equipment_id": "EXC-001", "metadata": {"firmware": "v2.1.4", "protocol": "OPC-UA"}, "metrics": {"engine_temp_c": 81.63, "hydraulic_psi": 3064.42, "rpm": 1807.36}}
{"timestamp": "2026-06-20T18:29:00Z", "equipment_id": "EXC-001", "metadata": {"firmware": "v2.1.4", "protocol": "OPC-UA"}, "metrics": {"engine_temp_c": 88.5, "hydraulic_psi": 2859.77, "rpm": 1782.9}}
{"timestamp": "2026-06-20T18:30:00Z", "equipment_id": "EXC-001", "metadata": {"firmware": "v2.1.4", "protocol": "OPC-UA"}, "metrics": {"engine_temp_c": 83.62, "hydraulic_psi": 2912.89, "rpm": 1822.08}}
{"timestamp": "2026-06-20T18:31:00Z", "equipment_id": "EXC-001", "metadata": {"firmware": "v2.1.4", "protocol": "OPC-UA"}, "metrics": {"engine_temp_c": 89.5, "hydraulic_psi": 2810.19, "rpm": 1826.87}}
{"timestamp": "2026-06-20T18:32:00Z", "equipment_id": "EXC-001", "metadata": {"firmware": "v2.1.4", "protocol": "OPC-UA"}, "metrics": {"engine_temp_c": 85.14, "hydraulic_psi": 3114.07, "rpm": 1799.44}}
{"timestamp": "2026-06-20T18:33:00Z", "equipment_id": "EXC-001", "metadata": {"firmware": "v2.1.4", "protocol": "OPC-UA"}, "metrics": {"engine_temp_c": 86.64, "hydraulic_psi": 3091.91, "rpm": 1760.6}}
{"timestamp": "2026-06-20T18:34:00Z", "equipment_id": "EXC-001", "metadata": {"firmware": "v2.1.4", "protocol": "OPC-UA"}, "metrics": {"engine_temp_c": 81.42, "hydraulic_psi": 2810.2, "rpm": 5247.8}}
{"timestamp": "2026-06-20T18:35:00Z", "equipment_id": "EXC-001", "metadata": {"firmware": "v2.1.4", "protocol": "OPC-UA"}, "metrics": {"engine_temp_c": 81.94, "hydraulic_psi": 3038.86, "rpm": 1796.04}}
{"timestamp": "2026-06-20T18:36:00Z", "equipment_id": "EXC-001", "metadata": {"firmware": "v2.1.4", "protocol": "OPC-UA"}, "metrics": {"engine_temp_c": 81.58, "hydraulic_psi": 3126.21, "rpm": 1786.77}}
{"timestamp": "2026-06-20T18:37:00Z", "equipment_id": "EXC-001", "metadata": {"firmware": "v2.1.4", "protocol": "OPC-UA"}, "metrics": {"engine_temp_c": 87.26, "hydraulic_psi": 3135.74, "rpm": 1753.35}}
{"timestamp": "2026-06-20T18:38:00Z", "equipment_id": "EXC-001", "metadata": {"firmware": "v2.1.4", "protocol": "OPC-UA"}, "metrics": {"engine_temp_c": 82.72, "hydraulic_psi": 3078.28, "rpm": 1785.32}}
{"timestamp": "2026-06-20T18:39:00Z", "equipment_id": "EXC-001", "metadata": {"firmware": "v2.1.4", "protocol": "OPC-UA"}, "metrics": {"engine_temp_c": 87.24, "hydraulic_psi": 3153.65, "rpm": 1760.57}}
{"timestamp": "2026-06-20T18:40:00Z", "equipment_id": "EXC-001", "metadata": {"firmware": "v2.1.4", "protocol": "OPC-UA"}, "metrics": {"engine_temp_c": 82.73, "hydraulic_psi": 2999.3, "rpm": 1815.76}}
{"timestamp": "2026-06-20T18:41:00Z", "equipment_id": "EXC-001", "metadata": {"firmware": "v2.1.4", "protocol": "OPC-UA"}, "metrics": {"engine_temp_c": 89.74, "hydraulic_psi": 3056.8, "rpm": 1810.89}}
{"timestamp": "2026-06-20T18:42:00Z", "equipment_id": "EXC-001", "metadata": {"firmware": "v2.1.4", "protocol": "OPC-UA"}, "metrics": {"engine_temp_c": 88.73, "hydraulic_psi": 2816.71, "rpm": 1771.4}}
{"timestamp": "2026-06-20T18:43:00Z", "equipment_id": "EXC-001", "metadata": {"firmware": "v2.1.4", "protocol": "OPC-UA"}, "metrics": {"engine_temp_c": 89.36, "hydraulic_psi": 2896.21, "rpm": 1831.66}}
{"timestamp": "2026-06-20T18:44:00Z", "equipment_id": "EXC-001", "metadata": {"firmware": "v2.1.4", "protocol": "OPC-UA"}, "metrics": {"engine_temp_c": 81.09, "hydraulic_psi": 2937.57, "rpm": 1833.06}}
{"timestamp": "2026-06-20T18:45:00Z", "equipment_id": "EXC-001", "metadata": {"firmware": "v2.1.4", "protocol": "OPC-UA"}, "metrics": {"engine_temp_c": 84.45, "hydraulic_psi": 2829.22, "rpm": 1753.22}}
{"timestamp": "2026-06-20T18:46:00Z", "equipment_id": "EXC-001", "metadata": {"firmware": "v2.1.4", "protocol": "OPC-UA"}, "metrics": {"engine_temp_c": 81.83, "hydraulic_psi": 2981.34, "rpm": 1797.59}}
{"timestamp": "2026-06-20T18:47:00Z", "equipment_id": "EXC-001", "metadata": {"firmware": "v2.1.4", "protocol": "OPC-UA"}, "metrics": {"engine_temp_c": 82.08, "hydraulic_psi": 3089.16, "rpm": 1752.4}}
{"timestamp": "2026-06-20T18:48:00Z", "equipment_id": "EXC-001", "metadata": {"firmware": "v2.1.4", "protocol": "OPC-UA"}, "metrics": {"engine_temp_c": 82.57, "hydraulic_psi": 2941.26, "rpm": 1792.01}}
{"timestamp": "2026-06-20T18:49:00Z", "equipment_id": "EXC-001", "metadata": {"firmware": "v2.1.4", "protocol": "OPC-UA"}, "metrics": {"engine_temp_c": 80.15, "hydraulic_psi": 3157.55, "rpm": 1801.25}}
{"timestamp": "2026-06-20T18:50:00Z", "equipment_id": "EXC-001", "metadata": {"firmware": "v2.1.4", "protocol": "OPC-UA"}, "metrics": {"engine_temp_c": 82.61, "hydraulic_psi": 2817.59, "rpm": 1778.46}}
{"timestamp": "2026-06-20T18:51:00Z", "equipment_id": "EXC-001", "metadata": {"firmware": "v2.1.4", "protocol": "OPC-UA"}, "metrics": {"engine_temp_c": 80.37, "hydraulic_psi": 2905.32, "rpm": 1804.23}}
{"timestamp": "2026-06-20T18:52:00Z", "equipment_id": "EXC-001", "metadata": {"firmware": "v2.1.4", "protocol": "OPC-UA"}, "metrics": {"engine_temp_c": 88.17, "hydraulic_psi": null, "rpm": 1816.54}}
{"timestamp": "2026-06-20T18:53:00Z", "equipment_id": "EXC-001", "metadata": {"firmware": "v2.1.4", "protocol": "OPC-UA"}, "metrics": {"engine_temp_c": 87.6, "hydraulic_psi": 3015.63, "rpm": 1769.11}}
{"timestamp": "2026-06-20T18:54:00Z", "equipment_id": "EXC-001", "metadata": {"firmware": "v2.1.4", "protocol": "OPC-UA"}, "metrics": {"engine_temp_c": 277.14, "hydraulic_psi": 3121.49, "rpm": 1797.49}}
{"timestamp": "2026-06-20T18:55:00Z", "equipment_id": "EXC-001", "metadata": {"firmware": "v2.1.4", "protocol": "OPC-UA"}, "metrics": {"engine_temp_c": 83.93, "hydraulic_psi": 6874.24, "rpm": 1803.97}}
{"timestamp": "2026-06-20T18:56:00Z", "equipment_id": "EXC-001", "metadata": {"firmware": "v2.1.4", "protocol": "OPC-UA"}, "metrics": {"engine_temp_c": 87.4, "hydraulic_psi": 2864.4, "rpm": 1848.18}}
{"timestamp": "2026-06-20T18:57:00Z", "equipment_id": "EXC-001", "metadata": {"firmware": "v2.1.4", "protocol": "OPC-UA"}, "metrics": {"engine_temp_c": 215.23, "hydraulic_psi": 3119.02, "rpm": 1753.17}}
{"timestamp": "2026-06-20T18:58:00Z", "equipment_id": "EXC-001", "metadata": {"firmware": "v2.1.4", "protocol": "OPC-UA"}, "metrics": {"engine_temp_c": 88.69, "hydraulic_psi": 2898.86, "rpm": 1769.45}}
{"timestamp": "2026-06-20T18:59:00Z", "equipment_id": "EXC-001", "metadata": {"firmware": "v2.1.4", "protocol": "OPC-UA"}, "metrics": {"engine_temp_c": 80.08, "hydraulic_psi": 2969.18, "rpm": 1820.18}}
