{"timestamp": "2026-06-21T05:00:00Z", "equipment_id": "CRSH-003", "metadata": {"firmware": "v2.1.4", "protocol": "OPC-UA"}, "metrics": {"engine_temp_c": 84.92, "hydraulic_psi": 3040.53, "rpm": 1785.24}}
{"timestamp": "2026-06-21T05:01:00Z", "equipment_id": "CRSH-003", "metadata": {"firmware": "v2.1.4", "protocol": "OPC-UA"}, "metrics": {"engine_temp_c": 80.34, "hydraulic_psi": 2977.44, "rpm": 1779.47}}
{"timestamp": "2026-06-21T05:02:00Z", "equipment_id": "CRSH-003", "metadata": {"firmware": "v2.1.4", "protocol": "OPC-UA"}, "metrics": {"engine_temp_c": 85.82, "hydraulic_psi": 2877.23, "rpm": 1797.84}}
{"timestamp": "2026-06-21T05:03:00Z", "equipment_id": "CRSH-003", "metadata": {"firmware": "v2.1.4", "protocol": "OPC-UA"}, "metrics": {"engine_temp_c": 88.18, "hydraulic_psi": 2903.94, "rpm": 1812.6}}
{"timestamp": "2026-06-21T05:04:00Z", "equipment_id": "CRSH-003", "metadata": {"firmware": "v2.1.4", "protocol": "OPC-UA"}, "metrics": {"engine_temp_c": 89.67, "hydraulic_psi": 2878.39, "rpm": 1779.86}}
{"timestamp": "2026-06-21T05:05:00Z", "equipment_id": "CRSH-003", "metadata": {"firmware": "v2.1.4", "protocol": "OPC-UA"}, "metrics": {"engine_temp_c": 87.19, "hydraulic_psi": 2949.49, "rpm": 1762.8}}
{"timestamp": "2026-06-21T05:06:00Z", "equipment_id": "CRSH-003", "metadata": {"firmware": "v2.1.4", "protocol": "OPC-UA"}, "metrics": {"engine_temp_c": 87.19, "hydraulic_psi": 2999.77, "rpm": 1839.31}}
{"timestamp": "2026-06-21T05:07:00Z", "equipment_id": "CRSH-003", "metadata": {"firmware": "v2.1.4", "protocol": "OPC-UA"}, "metrics": {"engine_temp_c": 87.98, "hydraulic_psi": 2942.53, "rpm": 1769.98}}
{"timestamp": "2026-06-21T05:08:00Z", "equipment_id": "CRSH-003", "metadata": {"firmware": "v2.1.4", "protocol": "OPC-UA"}, "metrics": {"engine_temp_c": 85.69, "hydraulic_psi": 2899.02, "rpm": 1831.76}}
{"timestamp": "2026-06-21T05:09:00Z", "equipment_id": "CRSH-003", "metadata": {"firmware": "v2.1.4", "protocol": "OPC-UA"}, "metrics": {"engine_temp_c": 89.03, "hydraulic_psi": 2828.14, "rpm": 1820.88}}
{"timestamp": "2026-06-21T05:10:00Z", "equipment_id": "CRSH-003", "metadata": {"firmware": "v2.1.4", "protocol": "OPC-UA"}, "metrics": {"engine_temp_c": 83.16, "hydraulic_psi": 3035.54, "rpm": 1763.07}}
{"timestamp": "2026-06-21T05:11:00Z", "equipment_id": "CRSH-003", "metadata": {"firmware": "v2.1.4", "protocol": "OPC-UA"}, "metrics": {"engine_temp_c": 87.86, "hydraulic_psi": 2984.81, "rpm": 1767.92}}
{"timestamp": "2026-06-21T05:12:00Z", "equipment_id": "CRSH-003", "metadata": {"firmware": "v2.1.4", "protocol": "OPC-UA"}, "metrics": {"engine_temp_c": 87.06, "hydraulic_psi": 2872.94, "rpm": 1844.22}}
{"timestamp": "2026-06-21T05:13:00Z", "equipment_id": "CRSH-003", "metadata": {"firmware": "v2.1.4", "protocol": "OPC-UA"}, "metrics": {"engine_temp_c": 84.02, "hydraulic_psi": 2829.8, "rpm": 1846.78}}
{"timestamp": "2026-06-21T05:14:00Z", "equipment_id": "CRSH-003", "metadata": {"firmware": "v2.1.4", "protocol": "OPC-UA"}, "metrics": {"engine_temp_c": 83.12, "hydraulic_psi": 2824.48, "rpm": 1793.39}}
{"timestamp": "2026-06-21T05:15:00Z", "equipment_id": "CRSH-003", "metadata": {"firmware": "v2.1.4", "protocol": "OPC-UA"}, "metrics": {"engine_temp_c": 84.17, "hydraulic_psi": 3131.95, "rpm": 1777.32}}
{"timestamp": "2026-06-21T05:16:00Z", "equipment_id": "CRSH-003", "metadata": {"firmware": "v2.1.4", "protocol": "OPC-UA"}, "metrics": {"engine_temp_c": 80.33, "hydraulic_psi": 2962.29, "rpm": 1796.78}}
{"timestamp": "2026-06-21T05:17:00Z", "equipment_id": "CRSH-003", "metadata": {"firmware": "v2.1.4", "protocol": "OPC-UA"}, "metrics": {"engine_temp_c": 84.91, "hydraulic_psi": 2975.67, "rpm": 1793.34}}
{"timestamp": "2026-06-21T05:18:00Z", "equipment_id": "CRSH-003", "metadata": {"firmware": "v2.1.4", "protocol": "OPC-UA"}, "metrics": {"engine_temp_c": 85.36, "hydraulic_psi": 3112.74, "rpm": 1827.49}}
{"timestamp": "2026-06-21T05:19:00Z", "equipment_id": "CRSH-003", "metadata": {"firmware": "v2.1.4", "protocol": "OPC-UA"}, "metrics": {"engine_temp_c": 83.44, "hydraulic_psi": 2820.94, "rpm": 1811.46}}
{"timestamp": "2026-06-21T05:20:00Z", "equipment_id": "CRSH-003", "metadata": {"firmware": "v2.1.4", "protocol": "OPC-UA"}, "metrics": {"engine_temp_c": 86.21, "hydraulic_psi": 3176.94, "rpm": 1846.92}}
{"timestamp": "2026-06-21T05:21:00Z", "equipment_id": "CRSH-003", "metadata": {"firmware": "v2.1.4", "protocol": "OPC-UA"}, "metrics": {"engine_temp_c": 89.54, "hydraulic_psi": 2943.84, "rpm": 1752.58}}
{"timestamp": "2026-06-21T05:22:00Z", "equipment_id": "CRSH-003", "metadata": {"firmware": "v2.1.4", "protocol": "OPC-UA"}, "metrics": {"engine_temp_c": 81.74, "hydraulic_psi": 2943.76, "rpm": 1835.66}}
{"timestamp": "2026-06-21T05:23:00Z", "equipment_id": "CRSH-003", "metadata": {"firmware": "v2.1.4", "protocol": "OPC-UA"}, "metrics": {"engine_temp_c": 84.03, "hydraulic_psi": 3054.4, "rpm": 1789.06}}
{"timestamp": "2026-06-21T05:24:00Z", "equipment_id": "CRSH-003", "metadata": {"firmware": "v2.1.4", "protocol": "OPC-UA"}, "metrics": {"engine_temp_c": 83.43, "hydraulic_psi": 3086.23, "rpm": 1808.19}}
{"timestamp": "2026-06-21T05:25:00Z", "equipment_id": "CRSH-003", "metadata": {"firmware": "v2.1.4", "protocol": "OPC-UA"}, "metrics": {"engine_temp_c": 89.75, "hydraulic_psi": 2892.53, "rpm": 1827.97}}
{"timestamp": "2026-06-21T05:26:00Z", "equipment_id": "CRSH-003", "metadata": {"firmware": "v2.1.4", "protocol": "OPC-UA"}, "metrics": {"engine_temp_c": 82.42, "hydraulic_psi": 3070.14, "rpm": 1800.98}}
{"timestamp": "2026-06-21T05:27:00Z", "equipment_id": "CRSH-003", "metadata": {"firmware": "v2.1.4", "protocol": "OPC-UA"}, "metrics": {"engine_temp_c": 81.3, "hydraulic_psi": 2818.81, "rpm": 1757.12}}
{"timestamp": "2026-06-21T05:28:00Z", "equipment_id": "CRSH-003", "metadata": {"firmware": "v2.1.4", "protocol": "OPC-UA"}, "metrics": {"engine_temp_c": 89.93, "hydraulic_psi": 3104.45, "rpm": 1840.49}}
{"timestamp": "2026-06-21T05:29:00Z", "equipment_id": "CRSH-003", "metadata": {"firmware": "v2.1.4", "protocol": "OPC-UA"}, "metrics": {"engine_temp_c": 80.23, "hydraulic_psi": 3046.35, "rpm": 1752.41}}
{"timestamp": "2026-06-21T05:30:00Z", "equipment_id": "CRSH-003", "metadata": {"firmware": "v2.1.4", "protocol": "OPC-UA"}, "metrics": {"engine_temp_c": 83.92, "hydraulic_psi": 3091.5, "rpm": 1809.1}}
{"timestamp": "2026-06-21T05:31:00Z", "equipment_id": "CRSH-003", "metadata": {"firmware": "v2.1.4", "protocol": "OPC-UA"}, "metrics": {"engine_temp_c": 85.19, "hydraulic_psi": 2815.96, "rpm": 1828.04}}
{"timestamp": "2026-06-21T05:32:00Z", "equipment_id": "CRSH-003", "metadata": {"firmware": "v2.1.4", "protocol": "OPC-UA"}, "metrics": {"engine_temp_c": 82.06, "hydraulic_psi": 2868.06, "rpm": 1814.81}}
{"timestamp": "2026-06-21T05:33:00Z", "equipment_id": "CRSH-003", "metadata": {"firmware": "v2.1.4", "protocol": "OPC-UA"}, "metrics": {"engine_temp_c": 87.42, "hydraulic_psi": 2918.07, "rpm": 1845.13}}
{"timestamp": "2026-06-21T05:34:00Z", "equipment_id": "CRSH-003", "metadata": {"firmware": "v2.1.4", "protocol": "OPC-UA"}, "metrics": {"engine_temp_c": 81.73, "hydraulic_psi": 3115.11, "rpm": 1776.42}}
{"timestamp": "2026-06-21T05:35:00Z", "equipment_id": "CRSH-003", "metadata": {"firmware": "v2.1.4", "protocol": "OPC-UA"}, "metrics": {"engine_temp_c": 84.04, "hydraulic_psi": 2917.05, "rpm": 1829.03}}
{"timestamp": "2026-06-21T05:36:00Z", "equipment_id": "CRSH-003", "metadata": {"firmware": "v2.1.4", "protocol": "OPC-UA"}, "metrics": {"engine_temp_c": 83.13, "hydraulic_psi": 2935.4, "rpm": 1757.35}}
{"timestamp": "2026-06-21T05:37:00Z", "equipment_id": "CRSH-003", "metadata": {"firmware": "v2.1.4", "protocol": "OPC-UA"}, "metrics": {"engine_temp_c": 81.33, "hydraulic_psi": 3077.04, "rpm": 1755.86}}
{"timestamp": "2026-06-21T05:38:00Z", "equipment_id": "CRSH-003", "metadata": {"firmware": "v2.1.4", "protocol": "OPC-UA"}, "metrics": {"engine_temp_c": 82.34, "hydraulic_psi": 3117.45, "rpm": 1760.24}}
{"timestamp": "2026-06-21T05:39:00Z", "equipment_id": "CRSH-003", "metadata": {"firmware": "v2.1.4", "protocol": "OPC-UA"}, "metrics": {"engine_temp_c": 83.66, "hydraulic_psi": 3042.17, "rpm": 1811.51}}
{"timestamp": "2026-06-21T05:40:00Z", "equipment_id": "CRSH-003", "metadata": {"firmware": "v2.1.4", "protocol": "OPC-UA"}, "metrics": {"engine_temp_c": 87.95, "hydraulic_psi": 2905.52, "rpm": 1750.06}}
{"timestamp": "2026-06-21T05:41:00Z", "equipment_id": "CRSH-003", "metadata": {"firmware": "v2.1.4", "protocol": "OPC-UA"}, "metrics": {"engine_temp_c": 338.63, "hydraulic_psi": 3171.96, "rpm": 1821.78}}
{"timestamp": "2026-06-21T05:42:00Z", "equipment_id": "CRSH-003", "metadata": {"firmware": "v2.1.4", "protocol": "OPC-UA"}, "metrics": {"engine_temp_c": 84.77, "hydraulic_psi": 3112.75, "rpm": 1763.06}}
{"timestamp": "2026-06-21T05:43:00Z", "equipment_id": "CRSH-003", "metadata": {"firmware": "v2.1.4", "protocol": "OPC-UA"}, "metrics": {"engine_temp_c": 88.32, "hydraulic_psi": 3084.52, "rpm": 1778.7}}
{"timestamp": "2026-06-21T05:44:00Z", "equipment_id": "CRSH-003", "metadata": {"firmware": "v2.1.4", "protocol": "OPC-UA"}, "metrics": {"engine_temp_c": 89.29, "hydraulic_psi": 2922.88, "rpm": 1791.61}}
{"timestamp": "2026-06-21T05:45:00Z", "equipment_id": "CRSH-003", "metadata": {"firmware": "v2.1.4", "protocol": "OPC-UA"}, "metrics": {"engine_temp_c": 274.78, "hydraulic_psi": 3174.08, "rpm": 1847.84}}
{"timestamp": "2026-06-21T05:46:00Z", "equipment_id": "CRSH-003", "metadata": {"firmware": "v2.1.4", "protocol": "OPC-UA"}, "metrics": {"engine_temp_c": 80.57, "hydraulic_psi": 3009.58, "rpm": 1817.4}}
{"timestamp": "2026-06-21T05:47:00Z", "equipment_id": "CRSH-003", "metadata": {"firmware": "v2.1.4", "protocol": "OPC-UA"}, "metrics": {"engine_temp_c": 87.9, "hydraulic_psi": 2834.35, "rpm": 1808.62}}
{"timestamp": "2026-06-21T05:48:00Z", "equipment_id": "CRSH-003", "metadata": {"firmware": "v2.1.4", "protocol": "OPC-UA"}, "metrics": {"engine_temp_c": 80.15, "hydraulic_psi": 3010.13, "rpm": 1751.0}}
{"timestamp": "2026-06-21T05:49:00Z", "equipment_id": "CRSH-003", "metadata": {"firmware": "v2.1.4", "protocol": "OPC-UA"}, "metrics": {"engine_temp_c": 82.27, "hydraulic_psi": 2975.02, "rpm": 1750.13}}
{"timestamp": "2026-06-21T05:50:00Z", "equipment_id": "CRSH-003", "metadata": {"firmware": "v2.1.4", "protocol": "OPC-UA"}, "metrics": {"engine_temp_c": 88.4, "hydraulic_psi": 3058.5, "rpm": 1809.09}}
{"timestamp": "2026-06-21T05:51:00Z", "equipment_id": "CRSH-003", "metadata": {"firmware": "v2.1.4", "protocol": "OPC-UA"}, "metrics": {"engine_temp_c": 80.18, "hydraulic_psi": 2806.42, "rpm": 1757.9}}
{"timestamp": "2026-06-21T05:52:00Z", "equipment_id": "CRSH-003", "metadata": {"firmware": "v2.1.4", "protocol": "OPC-UA"}, "metrics": {"engine_temp_c": 247.93, "hydraulic_psi": 3008.86, "rpm": 1764.86}}
{"timestamp": "2026-06-21T05:53:00Z", "equipment_id": "CRSH-003", "metadata": {"firmware": "v2.1.4", "protocol": "OPC-UA"}, "metrics": {"engine_temp_c": 85.18, "hydraulic_psi": 3092.8, "rpm": 1760.57}}
{"timestamp": "2026-06-21T05:54:00Z", "equipment_id": "CRSH-003", "metadata": {"firmware": "v2.1.4", "protocol": "OPC-UA"}, "metrics": {"engine_temp_c": 86.52, "hydraulic_psi": 2823.98, "rpm": 1753.71}}
{"timestamp": "2026-06-21T05:55:00Z", "equipment_id": "CRSH-003", "metadata": {"firmware": "v2.1.4", "protocol": "OPC-UA"}, "metrics": {"engine_temp_c": 88.3, "hydraulic_psi": 2849.61, "rpm": 1839.36}}
{"timestamp": "2026-06-21T05:56:00Z", "equipment_id": "CRSH-003", "metadata": {"firmware": "v2.1.4", "protocol": "OPC-UA"}, "metrics": {"engine_temp_c": 83.53, "hydraulic_psi": 3039.85, "rpm": 1788.22}}
{"timestamp": "2026-06-21T05:57:00Z", "equipment_id": "CRSH-003", "metadata": {"firmware": "v2.1.4", "protocol": "OPC-UA"}, "metrics": {"engine_temp_c": 86.56, "hydraulic_psi": 3174.35, "rpm": 1767.5}}
{"timestamp": "2026-06-21T05:58:00Z", "equipment_id": "CRSH-003", "metadata": {"firmware": "v2.1.4", "protocol": "OPC-UA"}, "metrics": {"engine_temp_c": 85.59, "hydraulic_psi": 3153.54, "rpm": 1810.26}}
{"timestamp": "2026-06-21T05:59:00Z", "equipment_id": "CRSH-003", "metadata": {"firmware": "v2.1.4", "protocol": "OPC-UA"}, "metrics": {"engine_temp_c": 87.69, "hydraulic_psi": 3027.54, "rpm": 1823.84}}
