{"timestamp": "2026-06-21T11:00:00Z", "equipment_id": "CRSH-003", "metadata": {"firmware": "v2.1.4", "protocol": "OPC-UA"}, "metrics": {"engine_temp_c": 82.01, "hydraulic_psi": 2852.31, "rpm": 1772.44}}
{"timestamp": "2026-06-21T11:01:00Z", "equipment_id": "CRSH-003", "metadata": {"firmware": "v2.1.4", "protocol": "OPC-UA"}, "metrics": {"engine_temp_c": 85.52, "hydraulic_psi": 3085.02, "rpm": 1768.0}}
{"timestamp": "2026-06-21T11:02:00Z", "equipment_id": "CRSH-003", "metadata": {"firmware": "v2.1.4", "protocol": "OPC-UA"}, "metrics": {"engine_temp_c": 83.47, "hydraulic_psi": 3188.1, "rpm": 1803.85}}
{"timestamp": "2026-06-21T11:03:00Z", "equipment_id": "CRSH-003", "metadata": {"firmware": "v2.1.4", "protocol": "OPC-UA"}, "metrics": {"engine_temp_c": 81.5, "hydraulic_psi": 2870.28, "rpm": 1758.6}}
{"timestamp": "2026-06-21T11:04:00Z", "equipment_id": "CRSH-003", "metadata": {"firmware": "v2.1.4", "protocol": "OPC-UA"}, "metrics": {"engine_temp_c": 81.87, "hydraulic_psi": 2867.52, "rpm": 1757.13}}
{"timestamp": "2026-06-21T11:05:00Z", "equipment_id": "CRSH-003", "metadata": {"firmware": "v2.1.4", "protocol": "OPC-UA"}, "metrics": {"engine_temp_c": 81.06, "hydraulic_psi": 3006.46, "rpm": 1789.61}}
{"timestamp": "2026-06-21T11:06:00Z", "equipment_id": "CRSH-003", "metadata": {"firmware": "v2.1.4", "protocol": "OPC-UA"}, "metrics": {"engine_temp_c": 89.18, "hydraulic_psi": 3110.76, "rpm": 1804.74}}
{"timestamp": "2026-06-21T11:07:00Z", "equipment_id": "CRSH-003", "metadata": {"firmware": "v2.1.4", "protocol": "OPC-UA"}, "metrics": {"engine_temp_c": 85.16, "hydraulic_psi": 3180.11, "rpm": 1836.73}}
{"timestamp": "2026-06-21T11:08:00Z", "equipment_id": "CRSH-003", "metadata": {"firmware": "v2.1.4", "protocol": "OPC-UA"}, "metrics": {"engine_temp_c": 88.13, "hydraulic_psi": 2937.4, "rpm": 1751.95}}
{"timestamp": "2026-06-21T11:09:00Z", "equipment_id": "CRSH-003", "metadata": {"firmware": "v2.1.4", "protocol": "OPC-UA"}, "metrics": {"engine_temp_c": 85.51, "hydraulic_psi": 3173.69, "rpm": 1809.43}}
{"timestamp": "2026-06-21T11:10:00Z", "equipment_id": "CRSH-003", "metadata": {"firmware": "v2.1.4", "protocol": "OPC-UA"}, "metrics": {"engine_temp_c": 81.02, "hydraulic_psi": 3131.75, "rpm": 1785.15}}
{"timestamp": "2026-06-21T11:11:00Z", "equipment_id": "CRSH-003", "metadata": {"firmware": "v2.1.4", "protocol": "OPC-UA"}, "metrics": {"engine_temp_c": 87.45, "hydraulic_psi": 3179.01, "rpm": 1765.13}}
{"timestamp": "2026-06-21T11:12:00Z", "equipment_id": "CRSH-003", "metadata": {"firmware": "v2.1.4", "protocol": "OPC-UA"}, "metrics": {"engine_temp_c": 81.39, "hydraulic_psi": 2929.84, "rpm": 1837.33}}
{"timestamp": "2026-06-21T11:13:00Z", "equipment_id": "CRSH-003", "metadata": {"firmware": "v2.1.4", "protocol": "OPC-UA"}, "metrics": {"engine_temp_c": 82.17, "hydraulic_psi": 3094.39, "rpm": 1849.85}}
{"timestamp": "2026-06-21T11:14:00Z", "equipment_id": "CRSH-003", "metadata": {"firmware": "v2.1.4", "protocol": "OPC-UA"}, "metrics": {"engine_temp_c": 86.07, "hydraulic_psi": 2932.11, "rpm": 1823.08}}
{"timestamp": "2026-06-21T11:15:00Z", "equipment_id": "CRSH-003", "metadata": {"firmware": "v2.1.4", "protocol": "OPC-UA"}, "metrics": {"engine_temp_c": 88.32, "hydraulic_psi": 2885.55, "rpm": 1768.48}}
{"timestamp": "2026-06-21T11:16:00Z", "equipment_id": "CRSH-003", "metadata": {"firmware": "v2.1.4", "protocol": "OPC-UA"}, "metrics": {"engine_temp_c": 87.15, "hydraulic_psi": 2921.63, "rpm": 1774.05}}
{"timestamp": "2026-06-21T11:17:00Z", "equipment_id": "CRSH-003", "metadata": {"firmware": "v2.1.4", "protocol": "OPC-UA"}, "metrics": {"engine_temp_c": 85.4, "hydraulic_psi": 3076.29, "rpm": 1759.04}}
{"timestamp": "2026-06-21T11:18:00Z", "equipment_id": "CRSH-003", "metadata": {"firmware": "v2.1.4", "protocol": "OPC-UA"}, "metrics": {"engine_temp_c": 85.26, "hydraulic_psi": 3145.15, "rpm": 1764.9}}
{"timestamp": "2026-06-21T11:19:00Z", "equipment_id": "CRSH-003", "metadata": {"firmware": "v2.1.4", "protocol": "OPC-UA"}, "metrics": {"engine_temp_c": 84.6, "hydraulic_psi": 3065.95, "rpm": 1752.21}}
{"timestamp": "2026-06-21T11:20:00Z", "equipment_id": "CRSH-003", "metadata": {"firmware": "v2.1.4", "protocol": "OPC-UA"}, "metrics": {"engine_temp_c": 82.92, "hydraulic_psi": 2897.86, "rpm": 1765.28}}
{"timestamp": "2026-06-21T11:21:00Z", "equipment_id": "CRSH-003", "metadata": {"firmware": "v2.1.4", "protocol": "OPC-UA"}, "metrics": {"engine_temp_c": 82.52, "hydraulic_psi": 2974.3, "rpm": 1820.03}}
{"timestamp": "2026-06-21T11:22:00Z", "equipment_id": "CRSH-003", "metadata": {"firmware": "v2.1.4", "protocol": "OPC-UA"}, "metrics": {"engine_temp_c": 88.3, "hydraulic_psi": 2910.46, "rpm": 1802.93}}
{"timestamp": "2026-06-21T11:23:00Z", "equipment_id": "CRSH-003", "metadata": {"firmware": "v2.1.4", "protocol": "OPC-UA"}, "metrics": {"engine_temp_c": 81.26, "hydraulic_psi": null, "rpm": 1772.71}}
{"timestamp": "2026-06-21T11:24:00Z", "equipment_id": "CRSH-003", "metadata": {"firmware": "v2.1.4", "protocol": "OPC-UA"}, "metrics": {"engine_temp_c": 83.07, "hydraulic_psi": 2852.82, "rpm": 1783.19}}
{"timestamp": "2026-06-21T11:25:00Z", "equipment_id": "CRSH-003", "metadata": {"firmware": "v2.1.4", "protocol": "OPC-UA"}, "metrics": {"engine_temp_c": 82.94, "hydraulic_psi": 2877.67, "rpm": 1821.53}}
{"timestamp": "2026-06-21T11:26:00Z", "equipment_id": "CRSH-003", "metadata": {"firmware": "v2.1.4", "protocol": "OPC-UA"}, "metrics": {"engine_temp_c": 324.76, "hydraulic_psi": 2993.97, "rpm": 1785.15}}
{"timestamp": "2026-06-21T11:27:00Z", "equipment_id": "CRSH-003", "metadata": {"firmware": "v2.1.4", "protocol": "OPC-UA"}, "metrics": {"engine_temp_c": 193.93, "hydraulic_psi": 2968.85, "rpm": 1810.44}}
{"timestamp": "2026-06-21T11:28:00Z", "equipment_id": "CRSH-003", "metadata": {"firmware": "v2.1.4", "protocol": "OPC-UA"}, "metrics": {"engine_temp_c": 80.62, "hydraulic_psi": 2833.33, "rpm": 1841.26}}
{"timestamp": "2026-06-21T11:29:00Z", "equipment_id": "CRSH-003", "metadata": {"firmware": "v2.1.4", "protocol": "OPC-UA"}, "metrics": {"engine_temp_c": 88.78, "hydraulic_psi": 2868.97, "rpm": 1847.07}}
{"timestamp": "2026-06-21T11:30:00Z", "equipment_id": "CRSH-003", "metadata": {"firmware": "v2.1.4", "protocol": "OPC-UA"}, "metrics": {"engine_temp_c": 88.13, "hydraulic_psi": 3114.86, "rpm": 1826.94}}
{"timestamp": "2026-06-21T11:31:00Z", "equipment_id": "CRSH-003", "metadata": {"firmware": "v2.1.4", "protocol": "OPC-UA"}, "metrics": {"engine_temp_c": 88.38, "hydraulic_psi": 3131.68, "rpm": 1786.49}}
{"timestamp": "2026-06-21T11:32:00Z", "equipment_id": "CRSH-003", "metadata": {"firmware": "v2.1.4", "protocol": "OPC-UA"}, "metrics": {"engine_temp_c": 88.12, "hydraulic_psi": 3024.38, "rpm": 1763.09}}
{"timestamp": "2026-06-21T11:33:00Z", "equipment_id": "CRSH-003", "metadata": {"firmware": "v2.1.4", "protocol": "OPC-UA"}, "metrics": {"engine_temp_c": 89.3, "hydraulic_psi": 3145.54, "rpm": 1826.09}}
{"timestamp": "2026-06-21T11:34:00Z", "equipment_id": "CRSH-003", "metadata": {"firmware": "v2.1.4", "protocol": "OPC-UA"}, "metrics": {"engine_temp_c": 80.23, "hydraulic_psi": 2943.94, "rpm": 1810.68}}
{"timestamp": "2026-06-21T11:35:00Z", "equipment_id": "CRSH-003", "metadata": {"firmware": "v2.1.4", "protocol": "OPC-UA"}, "metrics": {"engine_temp_c": 83.04, "hydraulic_psi": 3096.81, "rpm": 1754.27}}
{"timestamp": "2026-06-21T11:36:00Z", "equipment_id": "CRSH-003", "metadata": {"firmware": "v2.1.4", "protocol": "OPC-UA"}, "metrics": {"engine_temp_c": 81.99, "hydraulic_psi": 7318.34, "rpm": 1792.08}}
{"timestamp": "2026-06-21T11:37:00Z", "equipment_id": "CRSH-003", "metadata": {"firmware": "v2.1.4", "protocol": "OPC-UA"}, "metrics": {"engine_temp_c": 87.94, "hydraulic_psi": 2968.89, "rpm": 1780.38}}
{"timestamp": "2026-06-21T11:38:00Z", "equipment_id": "CRSH-003", "metadata": {"firmware": "v2.1.4", "protocol": "OPC-UA"}, "metrics": {"engine_temp_c": 81.65, "hydraulic_psi": 2815.5, "rpm": 1779.98}}
{"timestamp": "2026-06-21T11:39:00Z", "equipment_id": "CRSH-003", "metadata": {"firmware": "v2.1.4", "protocol": "OPC-UA"}, "metrics": {"engine_temp_c": 86.49, "hydraulic_psi": 2951.33, "rpm": 1828.49}}
{"timestamp": "2026-06-21T11:40:00Z", "equipment_id": "CRSH-003", "metadata": {"firmware": "v2.1.4", "protocol": "OPC-UA"}, "metrics": {"engine_temp_c": 85.2, "hydraulic_psi": 3092.56, "rpm": 1843.53}}
{"timestamp": "2026-06-21T11:41:00Z", "equipment_id": "CRSH-003", "metadata": {"firmware": "v2.1.4", "protocol": "OPC-UA"}, "metrics": {"engine_temp_c": 84.61, "hydraulic_psi": 3107.09, "rpm": 1835.87}}
{"timestamp": "2026-06-21T11:42:00Z", "equipment_id": "CRSH-003", "metadata": {"firmware": "v2.1.4", "protocol": "OPC-UA"}, "metrics": {"engine_temp_c": 88.26, "hydraulic_psi": 2881.67, "rpm": 1821.26}}
{"timestamp": "2026-06-21T11:43:00Z", "equipment_id": "CRSH-003", "metadata": {"firmware": "v2.1.4", "protocol": "OPC-UA"}, "metrics": {"engine_temp_c": 85.35, "hydraulic_psi": 3088.91, "rpm": 1758.6}}
{"timestamp": "2026-06-21T11:44:00Z", "equipment_id": "CRSH-003", "metadata": {"firmware": "v2.1.4", "protocol": "OPC-UA"}, "metrics": {"engine_temp_c": 85.84, "hydraulic_psi": 3198.8, "rpm": 1769.35}}
{"timestamp": "2026-06-21T11:45:00Z", "equipment_id": "CRSH-003", "metadata": {"firmware": "v2.1.4", "protocol": "OPC-UA"}, "metrics": {"engine_temp_c": 85.68, "hydraulic_psi": 3068.27, "rpm": 1788.76}}
{"timestamp": "2026-06-21T11:46:00Z", "equipment_id": "CRSH-003", "metadata": {"firmware": "v2.1.4", "protocol": "OPC-UA"}, "metrics": {"engine_temp_c": 89.13, "hydraulic_psi": 2824.65, "rpm": 1768.93}}
{"timestamp": "2026-06-21T11:47:00Z", "equipment_id": "CRSH-003", "metadata": {"firmware": "v2.1.4", "protocol": "OPC-UA"}, "metrics": {"engine_temp_c": 82.59, "hydraulic_psi": 3197.87, "rpm": 1761.04}}
{"timestamp": "2026-06-21T11:48:00Z", "equipment_id": "CRSH-003", "metadata": {"firmware": "v2.1.4", "protocol": "OPC-UA"}, "metrics": {"engine_temp_c": 83.72, "hydraulic_psi": 2872.05, "rpm": 5515.97}}
{"timestamp": "2026-06-21T11:49:00Z", "equipment_id": "CRSH-003", "metadata": {"firmware": "v2.1.4", "protocol": "OPC-UA"}, "metrics": {"engine_temp_c": 86.3, "hydraulic_psi": 3113.79, "rpm": 1831.71}}
{"timestamp": "2026-06-21T11:50:00Z", "equipment_id": "CRSH-003", "metadata": {"firmware": "v2.1.4", "protocol": "OPC-UA"}, "metrics": {"engine_temp_c": 84.9, "hydraulic_psi": 2926.23, "rpm": 1813.03}}
{"timestamp": "2026-06-21T11:51:00Z", "equipment_id": "CRSH-003", "metadata": {"firmware": "v2.1.4", "protocol": "OPC-UA"}, "metrics": {"engine_temp_c": 84.2, "hydraulic_psi": 3117.72, "rpm": 1821.42}}
{"timestamp": "2026-06-21T11:52:00Z", "equipment_id": "CRSH-003", "metadata": {"firmware": "v2.1.4", "protocol": "OPC-UA"}, "metrics": {"engine_temp_c": 85.02, "hydraulic_psi": 3009.8, "rpm": 1804.7}}
{"timestamp": "2026-06-21T11:53:00Z", "equipment_id": "CRSH-003", "metadata": {"firmware": "v2.1.4", "protocol": "OPC-UA"}, "metrics": {"engine_temp_c": 87.12, "hydraulic_psi": 2877.49, "rpm": 1765.3}}
{"timestamp": "2026-06-21T11:54:00Z", "equipment_id": "CRSH-003", "metadata": {"firmware": "v2.1.4", "protocol": "OPC-UA"}, "metrics": {"engine_temp_c": 87.15, "hydraulic_psi": 3109.38, "rpm": 1842.07}}
{"timestamp": "2026-06-21T11:55:00Z", "equipment_id": "CRSH-003", "metadata": {"firmware": "v2.1.4", "protocol": "OPC-UA"}, "metrics": {"engine_temp_c": 82.58, "hydraulic_psi": 3013.59, "rpm": 1776.47}}
{"timestamp": "2026-06-21T11:56:00Z", "equipment_id": "CRSH-003", "metadata": {"firmware": "v2.1.4", "protocol": "OPC-UA"}, "metrics": {"engine_temp_c": 84.89, "hydraulic_psi": null, "rpm": 1826.84}}
{"timestamp": "2026-06-21T11:57:00Z", "equipment_id": "CRSH-003", "metadata": {"firmware": "v2.1.4", "protocol": "OPC-UA"}, "metrics": {"engine_temp_c": 83.73, "hydraulic_psi": 3085.16, "rpm": 4358.4}}
{"timestamp": "2026-06-21T11:58:00Z", "equipment_id": "CRSH-003", "metadata": {"firmware": "v2.1.4", "protocol": "OPC-UA"}, "metrics": {"engine_temp_c": 83.2, "hydraulic_psi": 3030.4, "rpm": 1828.09}}
{"timestamp": "2026-06-21T11:59:00Z", "equipment_id": "CRSH-003", "metadata": {"firmware": "v2.1.4", "protocol": "OPC-UA"}, "metrics": {"engine_temp_c": 89.4, "hydraulic_psi": 2890.73, "rpm": 1779.75}}
